[
    {
        "key": "division_template|name",
        "original": "Royal Guard",
        "translation": "",
        "stage": 0
    },
    {
        "key": "division_template#|name",
        "original": "Militia",
        "translation": "",
        "stage": 0
    },
    {
        "key": "units|division|name",
        "original": "Royal Afghan Household Division",
        "translation": "",
        "stage": 0
    },
    {
        "key": "units|division|division_template",
        "original": "Royal Guard",
        "translation": "",
        "stage": 0
    },
    {
        "key": "units|division#|division_template",
        "original": "Militia",
        "translation": "",
        "stage": 0
    },
    {
        "key": "units|division##|division_template",
        "original": "Militia",
        "translation": "",
        "stage": 0
    },
    {
        "key": "units|division###|division_template",
        "original": "Militia",
        "translation": "",
        "stage": 0
    },
    {
        "key": "units|division####|division_template",
        "original": "Militia",
        "translation": "",
        "stage": 0
    },
    {
        "key": "units|division#####|division_template",
        "original": "Militia",
        "translation": "",
        "stage": 0
    },
    {
        "key": "units|division######|division_template",
        "original": "Militia",
        "translation": "",
        "stage": 0
    },
    {
        "key": "units|division#######|division_template",
        "original": "Militia",
        "translation": "",
        "stage": 0
    },
    {
        "key": "units|division########|division_template",
        "original": "Militia",
        "translation": "",
        "stage": 0
    }
]